datactl/__init__.py
datactl/celery.py
datactl/data_config.py
datactl/datactl.py
datactl/mongodb.py
datactl/rabbitmq.py
datactl/redis.py
datactl/request.py
datactl/utils.py
datactl-0.1.1.dist-info/entry_points.txt
datactl-0.1.1.dist-info/WHEEL
datactl-0.1.1.dist-info/METADATA
datactl-0.1.1.dist-info/RECORD
